ttbot/TikTok.py
ttbot/__init__.py
ttbot-0.0.2.dist-info/METADATA
ttbot-0.0.2.dist-info/WHEEL
ttbot-0.0.2.dist-info/top_level.txt
ttbot-0.0.2.dist-info/RECORD
